finxos/__init__.py
finxos/data/__init__.py
finxos/data/data_api.py
finxos/data/rest_agent.py
finxos-1.0.0.dist-info/LICENSE
finxos-1.0.0.dist-info/METADATA
finxos-1.0.0.dist-info/WHEEL
finxos-1.0.0.dist-info/top_level.txt
finxos-1.0.0.dist-info/RECORD
