Metadata-Version: 2.1
Name: finxos
Version: 1.0.0
Summary: Open source data tools.
Home-page: https://github.com/PKUJohnson/finxOS
Author: PKUJohnson
Author-email: UNKNOWN
License: Apache 2.0
Keywords: data,crawler,free
Platform: UNKNOWN
Classifier: Development Status :: 4 - Beta
Classifier: Intended Audience :: Developers
Classifier: Intended Audience :: Education
Classifier: Intended Audience :: End Users/Desktop
Classifier: Intended Audience :: Financial and Insurance Industry
Classifier: Intended Audience :: Information Technology
Classifier: Intended Audience :: Science/Research
Classifier: License :: OSI Approved :: Apache Software License
Classifier: Natural Language :: Chinese (Simplified)
Classifier: Natural Language :: English
Classifier: Operating System :: Microsoft :: Windows
Classifier: Operating System :: Unix
Classifier: Programming Language :: Python :: 3.6
Requires-Dist: pandas
Requires-Dist: requests
Requires-Dist: numpy
